Metadata-Version: 2.1
Name: luc-distributions
Version: 0.1
Summary: Gaussian distributions
Home-page: UNKNOWN
Author: Lucas Elbert Suryana
Author-email: lucaselbert@gmail.com
License: UNKNOWN
Platform: UNKNOWN
